randomForestUltra/RFUltra.py
randomForestUltra/__init__.py
randomForestUltra/plotROC.py
randomForestUltra-0.5.0.dist-info/LICENSE
randomForestUltra-0.5.0.dist-info/METADATA
randomForestUltra-0.5.0.dist-info/WHEEL
randomForestUltra-0.5.0.dist-info/top_level.txt
randomForestUltra-0.5.0.dist-info/RECORD
