Metadata-Version: 2.1
Name: randomForestUltra
Version: 0.5.0
Summary: 2023-11-09 11:23:56It supports multi-objective variable and multi-fold random forest, and can calculate P value through random permutation.
Home-page: UNKNOWN
Author: Haiyang Hou
Author-email: 2868582991@qq.com
License: UNKNOWN
Keywords: random forest,multi-fold,multi-objective,P value
Platform: UNKNOWN
Requires-Python: >=3.7
License-File: LICENSE
Requires-Dist: numpy
Requires-Dist: pandas
Requires-Dist: tqdm
Requires-Dist: seaborn
Requires-Dist: matplotlib
Requires-Dist: scipy
Requires-Dist: scikit-learn
